bookapi_t_sb032622/__init__.py
bookapi_t_sb032622/api.py
bookapi_t_sb032622-1.0.0.dist-info/WHEEL
bookapi_t_sb032622-1.0.0.dist-info/METADATA
bookapi_t_sb032622-1.0.0.dist-info/RECORD
