Metadata-Version: 2.1
Name: bookapi-t-sb032622
Version: 1.0.0
Summary: 
Author: Your Name
Author-email: you@example.com
Requires-Python: >=3.7,<4.0
Classifier: Programming Language :: Python :: 3
Classifier: Programming Language :: Python :: 3.10
Classifier: Programming Language :: Python :: 3.7
Classifier: Programming Language :: Python :: 3.8
Classifier: Programming Language :: Python :: 3.9
Requires-Dist: Flask (>=2.0.3,<3.0.0)
Requires-Dist: Flask-RESTful (>=0.3.9,<0.4.0)
